{"assets/fonts/Aileron-Black.otf":["assets/fonts/Aileron-Black.otf"],"assets/fonts/Aileron-Bold.otf":["assets/fonts/Aileron-Bold.otf"],"assets/fonts/Aileron-Heavy.otf":["assets/fonts/Aileron-Heavy.otf"],"assets/fonts/Aileron-Light.otf":["assets/fonts/Aileron-Light.otf"],"assets/fonts/Aileron-Regular.otf":["assets/fonts/Aileron-Regular.otf"],"assets/fonts/Aileron-SemiBold.otf":["assets/fonts/Aileron-SemiBold.otf"],"assets/fonts/Aileron-Thin.otf":["assets/fonts/Aileron-Thin.otf"],"assets/fonts/Aileron-UltraLight.otf":["assets/fonts/Aileron-UltraLight.otf"],"assets/fonts/Brittany.ttf":["assets/fonts/Brittany.ttf"],"assets/fonts/Cormorant-Bold.ttf":["assets/fonts/Cormorant-Bold.ttf"],"assets/fonts/Cormorant-Light.ttf":["assets/fonts/Cormorant-Light.ttf"],"assets/fonts/Cormorant-Medium.ttf":["assets/fonts/Cormorant-Medium.ttf"],"assets/fonts/Cormorant-Regular.ttf":["assets/fonts/Cormorant-Regular.ttf"],"assets/fonts/Cormorant-SemiBold.ttf":["assets/fonts/Cormorant-SemiBold.ttf"],"assets/fonts/CormorantGaramond-Bold.ttf":["assets/fonts/CormorantGaramond-Bold.ttf"],"assets/fonts/CormorantGaramond-Light.ttf":["assets/fonts/CormorantGaramond-Light.ttf"],"assets/fonts/CormorantGaramond-Medium.ttf":["assets/fonts/CormorantGaramond-Medium.ttf"],"assets/fonts/CormorantGaramond-Regular.ttf":["assets/fonts/CormorantGaramond-Regular.ttf"],"assets/fonts/CormorantGaramond-SemiBold.ttf":["assets/fonts/CormorantGaramond-SemiBold.ttf"],"assets/fonts/GreatVibes-Regular.ttf":["assets/fonts/GreatVibes-Regular.ttf"],"assets/fonts/JosefinSans-Bold.ttf":["assets/fonts/JosefinSans-Bold.ttf"],"assets/fonts/JosefinSans-Light.ttf":["assets/fonts/JosefinSans-Light.ttf"],"assets/fonts/JosefinSans-Medium.ttf":["assets/fonts/JosefinSans-Medium.ttf"],"assets/fonts/JosefinSans-Regular.ttf":["assets/fonts/JosefinSans-Regular.ttf"],"assets/fonts/JosefinSans-SemiBold.ttf":["assets/fonts/JosefinSans-SemiBold.ttf"],"assets/fonts/JosefinSans-Thin.ttf":["assets/fonts/JosefinSans-Thin.ttf"],"assets/fonts/LavishlyYours-Regular.ttf":["assets/fonts/LavishlyYours-Regular.ttf"],"assets/fonts/QuickSand-Bold.ttf":["assets/fonts/QuickSand-Bold.ttf"],"assets/fonts/QuickSand-Light.ttf":["assets/fonts/QuickSand-Light.ttf"],"assets/fonts/QuickSand-Medium.ttf":["assets/fonts/QuickSand-Medium.ttf"],"assets/fonts/QuickSand-Regular.ttf":["assets/fonts/QuickSand-Regular.ttf"],"assets/fonts/QuickSand-SemiBold.ttf":["assets/fonts/QuickSand-SemiBold.ttf"],"assets/images/373204500452687873.mp4":["assets/images/373204500452687873.mp4"],"assets/images/_ (11).jpeg":["assets/images/_ (11).jpeg"],"assets/images/_ (19).jpeg":["assets/images/_ (19).jpeg"],"assets/images/_ (21).jpeg":["assets/images/_ (21).jpeg"],"assets/images/_ (22).jpeg":["assets/images/_ (22).jpeg"],"assets/images/_ (8).jpeg":["assets/images/_ (8).jpeg"],"assets/images/flower_top_falling.jpeg":["assets/images/flower_top_falling.jpeg"]}